rolldice/__init__.py
rolldice/rolldice.py
py_rolldice-0.4.0.dist-info/LICENSE
py_rolldice-0.4.0.dist-info/METADATA
py_rolldice-0.4.0.dist-info/WHEEL
py_rolldice-0.4.0.dist-info/top_level.txt
py_rolldice-0.4.0.dist-info/RECORD
