Metadata-Version: 2.1
Name: py-rolldice
Version: 0.4.0
Summary: A module for parsing dice notation
Home-page: https://github.com/ThePlasmaRailgun/py-rolldice
Author: Finian Blackett
Author-email: spamsuckersunited@gmail.com
License: UNKNOWN
Platform: UNKNOWN
Classifier: Programming Language :: Python :: 3.6
Classifier: License :: OSI Approved :: GNU General Public License v3 (GPLv3)
Classifier: Operating System :: OS Independent
